<hydraMenu>
  <menu name="subsys_cmds">
    <menu name="Thruster">
      <cmd name="SetThrusterI2c"/>
      <cmd name="ClearThrusterI2c"/>
      <cmd name="FireThruster"/>
      <cmd name="StopThruster"/>
      <cmd name="SetThrusterMode"/>
      <cmd name="ThrusterStartGroundTest"/>
      <cmd name="ThrusterStopGroundTest"/>
      <cmd name="ThusterResetErrorCode"/>
    </menu>
    <menu name="Gecko">
      <cmd name="SetGeckoRegister"/>
      <cmd name="SetGeckoTREN"/>
      <cmd name="ClearDoneFlags"/>
      <cmd name="StartErase"/>
      <cmd name="StartSample"/>
      <cmd name="StartReadout"/>
      <cmd name="SetFlashAddr"/>
      <cmd name="SetNFrames"/>
      <cmd name="SetReadoutImageType"/>
      <cmd name="SetSensorOnOff"/>
      <cmd name="SetFrameRate"/>
      <cmd name="SetOffsetGain"/>
      <cmd name="SetExposureTime"/>
      <cmd name="StartImageCaptureTask"/>
    </menu>
    <menu name="Atmolite">
      <cmd name="SetATMLTTREN"/>
      <cmd name="SetATMLTHeater"/>
    </menu>
    <menu name="SQ UHF">
      <cmd name="EnableSQUHF"/>
      <cmd name="EnableSQUHFTREN"/>
      <cmd name="SetSQENTREN"/>
      <cmd name="Escape"/>
      <cmd name="SwitchToBinaryMode"/>
      <cmd name="SwitchToDecimalMode"/>
      <cmd name="SwitchToTwoComplementMode"/>
      <cmd name="LoadDefaultChannel"/>
      <cmd name="PresetChannel"/>
      <cmd name="EchoOn"/>
      <cmd name="EchoOff"/>
      <cmd name="AFCEnable"/>
      <cmd name="AFCDisable"/>
      <cmd name="Initialize"/>
      <cmd name="ReceiveMode"/>
      <cmd name="TransmitMode"/>
      <cmd name="SWDAnnounciateOn"/>
      <cmd name="SWDAnnounciateOff"/>
      <cmd name="ClearCounters"/>
      <cmd name="LoadRegister"/>
      <cmd name="LoadSWD"/>
      <cmd name="TransmitCarrier"/>
      <cmd name="TransmitPN9Test"/>
    </menu>
    <menu name="XBand">
    </menu>
  </menu>

</hydraMenu>
